<?xml version="1.0" encoding="utf-8" ?>
<c2layout>
    <name>gameplay</name>
    <sid>8873350371196689</sid>
    <event-sheet>main</event-sheet>
    <size>
        <width>640</width>
        <height>960</height>
    </size>
    <margins>
        <horizontal>2000</horizontal>
        <vertical>2000</vertical>
    </margins>
    <unbounded-scrolling>1</unbounded-scrolling>
    <layers>
        <layer name="background" sid="8722530541249526">
            <initially-visible>1</initially-visible>
            <background-color>102,102,153</background-color>
            <transparent>0</transparent>
            <parallax>
                <x>1</x>
                <y>1</y>
            </parallax>
            <zoom-rate>1</zoom-rate>
            <opacity>1</opacity>
            <force-own-texture>0</force-own-texture>
            <blend-mode>0</blend-mode>
            <effect-fallback>0</effect-fallback>
            <instances />
            <effects />
        </layer>
        <layer name="screen" sid="1248766231708009">
            <initially-visible>1</initially-visible>
            <background-color>255,255,255</background-color>
            <transparent>1</transparent>
            <parallax>
                <x>1</x>
                <y>1</y>
            </parallax>
            <zoom-rate>1</zoom-rate>
            <opacity>1</opacity>
            <force-own-texture>0</force-own-texture>
            <blend-mode>0</blend-mode>
            <effect-fallback>0</effect-fallback>
            <instances>
                <instance type="screen" uid="20">
                    <properties>
                        <initial-visibility>Invisible</initial-visibility>
                        <initial-animation>Default</initial-animation>
                        <initial-frame>0</initial-frame>
                        <collisions>Enabled</collisions>
                    </properties>
                    <instance-variables>
                        <number>1</number>
                    </instance-variables>
                    <behavior-instances>
                        <behavior-instance type="NoSave" />
                    </behavior-instances>
                    <blend-mode>0</blend-mode>
                    <effect-fallback>0</effect-fallback>
                    <world>
                        <x>320</x>
                        <y>480</y>
                        <z>0</z>
                        <width>640</width>
                        <height>960</height>
                        <depth>0</depth>
                        <hotspotX>0.5</hotspotX>
                        <hotspotY>0.5</hotspotY>
                        <angle>0</angle>
                        <opacity>0.100000001</opacity>
                    </world>
                </instance>
                <instance type="solidBloc" uid="18">
                    <properties>
                        <initial-visibility>Visible</initial-visibility>
                        <initial-animation>Default</initial-animation>
                        <initial-frame>0</initial-frame>
                        <collisions>Enabled</collisions>
                    </properties>
                    <behavior-instances>
                        <behavior-instance type="Physics">
                            <properties>
                                <immovable>Yes</immovable>
                                <collision-mask>Bounding box</collision-mask>
                                <prevent-rotation>Yes</prevent-rotation>
                                <density>1</density>
                                <friction>0.5</friction>
                                <elasticity>0.2</elasticity>
                                <linear-damping>0</linear-damping>
                                <angular-damping>0.01</angular-damping>
                                <bullet>No</bullet>
                                <initial-state>Enabled</initial-state>
                            </properties>
                        </behavior-instance>
                        <behavior-instance type="NoSave" />
                    </behavior-instances>
                    <blend-mode>0</blend-mode>
                    <effect-fallback>0</effect-fallback>
                    <world>
                        <x>640</x>
                        <y>479.5</y>
                        <z>0</z>
                        <width>3</width>
                        <height>1004</height>
                        <depth>0</depth>
                        <hotspotX>0.5</hotspotX>
                        <hotspotY>0.5</hotspotY>
                        <angle>0</angle>
                        <opacity>1</opacity>
                    </world>
                </instance>
                <instance type="solidBloc" uid="11">
                    <properties>
                        <initial-visibility>Visible</initial-visibility>
                        <initial-animation>Default</initial-animation>
                        <initial-frame>0</initial-frame>
                        <collisions>Enabled</collisions>
                    </properties>
                    <behavior-instances>
                        <behavior-instance type="Physics">
                            <properties>
                                <immovable>Yes</immovable>
                                <collision-mask>Bounding box</collision-mask>
                                <prevent-rotation>Yes</prevent-rotation>
                                <density>1</density>
                                <friction>0.5</friction>
                                <elasticity>0.2</elasticity>
                                <linear-damping>0</linear-damping>
                                <angular-damping>0.01</angular-damping>
                                <bullet>No</bullet>
                                <initial-state>Enabled</initial-state>
                            </properties>
                        </behavior-instance>
                        <behavior-instance type="NoSave" />
                    </behavior-instances>
                    <blend-mode>0</blend-mode>
                    <effect-fallback>0</effect-fallback>
                    <world>
                        <x>0</x>
                        <y>479</y>
                        <z>0</z>
                        <width>3</width>
                        <height>1004</height>
                        <depth>0</depth>
                        <hotspotX>0.5</hotspotX>
                        <hotspotY>0.5</hotspotY>
                        <angle>0</angle>
                        <opacity>1</opacity>
                    </world>
                </instance>
                <instance type="screen" uid="32">
                    <properties>
                        <initial-visibility>Invisible</initial-visibility>
                        <initial-animation>Default</initial-animation>
                        <initial-frame>0</initial-frame>
                        <collisions>Enabled</collisions>
                    </properties>
                    <instance-variables>
                        <number>2</number>
                    </instance-variables>
                    <behavior-instances>
                        <behavior-instance type="NoSave" />
                    </behavior-instances>
                    <blend-mode>0</blend-mode>
                    <effect-fallback>0</effect-fallback>
                    <world>
                        <x>968</x>
                        <y>480</y>
                        <z>0</z>
                        <width>640</width>
                        <height>960</height>
                        <depth>0</depth>
                        <hotspotX>0.5</hotspotX>
                        <hotspotY>0.5</hotspotY>
                        <angle>0</angle>
                        <opacity>0.100000001</opacity>
                    </world>
                </instance>
                <instance type="screen" uid="38">
                    <properties>
                        <initial-visibility>Invisible</initial-visibility>
                        <initial-animation>Default</initial-animation>
                        <initial-frame>0</initial-frame>
                        <collisions>Enabled</collisions>
                    </properties>
                    <instance-variables>
                        <number>3</number>
                    </instance-variables>
                    <behavior-instances>
                        <behavior-instance type="NoSave" />
                    </behavior-instances>
                    <blend-mode>0</blend-mode>
                    <effect-fallback>0</effect-fallback>
                    <world>
                        <x>1633</x>
                        <y>487</y>
                        <z>0</z>
                        <width>640</width>
                        <height>960</height>
                        <depth>0</depth>
                        <hotspotX>0.5</hotspotX>
                        <hotspotY>0.5</hotspotY>
                        <angle>0</angle>
                        <opacity>0.100000001</opacity>
                    </world>
                </instance>
                <instance type="screen" uid="51">
                    <properties>
                        <initial-visibility>Invisible</initial-visibility>
                        <initial-animation>Default</initial-animation>
                        <initial-frame>0</initial-frame>
                        <collisions>Enabled</collisions>
                    </properties>
                    <instance-variables>
                        <number>4</number>
                    </instance-variables>
                    <behavior-instances>
                        <behavior-instance type="NoSave" />
                    </behavior-instances>
                    <blend-mode>0</blend-mode>
                    <effect-fallback>0</effect-fallback>
                    <world>
                        <x>978</x>
                        <y>-537</y>
                        <z>0</z>
                        <width>640</width>
                        <height>960</height>
                        <depth>0</depth>
                        <hotspotX>0.5</hotspotX>
                        <hotspotY>0.5</hotspotY>
                        <angle>0</angle>
                        <opacity>0.100000001</opacity>
                    </world>
                </instance>
            </instances>
            <effects />
        </layer>
        <layer name="boutons" sid="5720985259907512">
            <initially-visible>1</initially-visible>
            <background-color>255,255,255</background-color>
            <transparent>1</transparent>
            <parallax>
                <x>1</x>
                <y>1</y>
            </parallax>
            <zoom-rate>1</zoom-rate>
            <opacity>1</opacity>
            <force-own-texture>0</force-own-texture>
            <blend-mode>0</blend-mode>
            <effect-fallback>0</effect-fallback>
            <instances>
                <instance type="btnUpgradeBack" uid="46">
                    <properties>
                        <initial-visibility>Visible</initial-visibility>
                        <initial-animation>Default</initial-animation>
                        <initial-frame>0</initial-frame>
                        <collisions>Enabled</collisions>
                    </properties>
                    <behavior-instances>
                        <behavior-instance type="NoSave" />
                    </behavior-instances>
                    <blend-mode>0</blend-mode>
                    <effect-fallback>0</effect-fallback>
                    <world>
                        <x>653</x>
                        <y>401</y>
                        <z>0</z>
                        <width>527</width>
                        <height>106</height>
                        <depth>0</depth>
                        <hotspotX>0</hotspotX>
                        <hotspotY>0</hotspotY>
                        <angle>0</angle>
                        <opacity>1</opacity>
                    </world>
                </instance>
                <instance type="arrow" uid="8">
                    <properties>
                        <initial-visibility>Visible</initial-visibility>
                        <initial-animation>Default</initial-animation>
                        <initial-frame>0</initial-frame>
                        <collisions>Enabled</collisions>
                    </properties>
                    <instance-variables>
                        <goto>2</goto>
                    </instance-variables>
                    <behavior-instances>
                        <behavior-instance type="NoSave" />
                    </behavior-instances>
                    <blend-mode>0</blend-mode>
                    <effect-fallback>0</effect-fallback>
                    <world>
                        <x>571</x>
                        <y>902.507629395</y>
                        <z>0</z>
                        <width>123</width>
                        <height>92</height>
                        <depth>0</depth>
                        <hotspotX>0.502645493</hotspotX>
                        <hotspotY>0.441176474</hotspotY>
                        <angle>0</angle>
                        <opacity>1</opacity>
                    </world>
                </instance>
                <instance type="arrow" uid="10">
                    <properties>
                        <initial-visibility>Visible</initial-visibility>
                        <initial-animation>Default</initial-animation>
                        <initial-frame>0</initial-frame>
                        <collisions>Enabled</collisions>
                    </properties>
                    <instance-variables>
                        <goto>1</goto>
                    </instance-variables>
                    <behavior-instances>
                        <behavior-instance type="NoSave" />
                    </behavior-instances>
                    <blend-mode>0</blend-mode>
                    <effect-fallback>0</effect-fallback>
                    <world>
                        <x>713.995727539</x>
                        <y>907.752807617</y>
                        <z>0</z>
                        <width>123</width>
                        <height>92</height>
                        <depth>0</depth>
                        <hotspotX>0.502645493</hotspotX>
                        <hotspotY>0.441176474</hotspotY>
                        <angle>3.141592741</angle>
                        <opacity>1</opacity>
                    </world>
                </instance>
                <instance type="arrow" uid="12">
                    <properties>
                        <initial-visibility>Visible</initial-visibility>
                        <initial-animation>Default</initial-animation>
                        <initial-frame>0</initial-frame>
                        <collisions>Enabled</collisions>
                    </properties>
                    <instance-variables>
                        <goto>3</goto>
                    </instance-variables>
                    <behavior-instances>
                        <behavior-instance type="NoSave" />
                    </behavior-instances>
                    <blend-mode>0</blend-mode>
                    <effect-fallback>0</effect-fallback>
                    <world>
                        <x>1216.006591797</x>
                        <y>906.006591797</y>
                        <z>0</z>
                        <width>123</width>
                        <height>92</height>
                        <depth>0</depth>
                        <hotspotX>0.502645493</hotspotX>
                        <hotspotY>0.441176474</hotspotY>
                        <angle>0</angle>
                        <opacity>1</opacity>
                    </world>
                </instance>
                <instance type="arrow" uid="13">
                    <properties>
                        <initial-visibility>Visible</initial-visibility>
                        <initial-animation>Default</initial-animation>
                        <initial-frame>0</initial-frame>
                        <collisions>Enabled</collisions>
                    </properties>
                    <instance-variables>
                        <goto>2</goto>
                    </instance-variables>
                    <behavior-instances>
                        <behavior-instance type="NoSave" />
                    </behavior-instances>
                    <blend-mode>0</blend-mode>
                    <effect-fallback>0</effect-fallback>
                    <world>
                        <x>1384</x>
                        <y>910</y>
                        <z>0</z>
                        <width>123</width>
                        <height>92</height>
                        <depth>0</depth>
                        <hotspotX>0.502645493</hotspotX>
                        <hotspotY>0.441176474</hotspotY>
                        <angle>3.141592741</angle>
                        <opacity>1</opacity>
                    </world>
                </instance>
                <instance type="btnBeeBack" uid="44">
                    <properties>
                        <initial-visibility>Visible</initial-visibility>
                        <initial-animation>Default</initial-animation>
                        <initial-frame>0</initial-frame>
                        <collisions>Enabled</collisions>
                    </properties>
                    <behavior-instances>
                        <behavior-instance type="NoSave" />
                    </behavior-instances>
                    <blend-mode>0</blend-mode>
                    <effect-fallback>0</effect-fallback>
                    <world>
                        <x>1330</x>
                        <y>346</y>
                        <z>0</z>
                        <width>527</width>
                        <height>106</height>
                        <depth>0</depth>
                        <hotspotX>0</hotspotX>
                        <hotspotY>0</hotspotY>
                        <angle>0</angle>
                        <opacity>1</opacity>
                    </world>
                </instance>
                <instance type="btnUpgradeBack" uid="45">
                    <properties>
                        <initial-visibility>Visible</initial-visibility>
                        <initial-animation>Default</initial-animation>
                        <initial-frame>0</initial-frame>
                        <collisions>Enabled</collisions>
                    </properties>
                    <behavior-instances>
                        <behavior-instance type="NoSave" />
                    </behavior-instances>
                    <blend-mode>0</blend-mode>
                    <effect-fallback>0</effect-fallback>
                    <world>
                        <x>653</x>
                        <y>652</y>
                        <z>0</z>
                        <width>527</width>
                        <height>106</height>
                        <depth>0</depth>
                        <hotspotX>0</hotspotX>
                        <hotspotY>0</hotspotY>
                        <angle>0</angle>
                        <opacity>1</opacity>
                    </world>
                </instance>
                <instance type="btnUpgradeBack" uid="47">
                    <properties>
                        <initial-visibility>Visible</initial-visibility>
                        <initial-animation>Default</initial-animation>
                        <initial-frame>0</initial-frame>
                        <collisions>Enabled</collisions>
                    </properties>
                    <behavior-instances>
                        <behavior-instance type="NoSave" />
                    </behavior-instances>
                    <blend-mode>0</blend-mode>
                    <effect-fallback>0</effect-fallback>
                    <world>
                        <x>653</x>
                        <y>524</y>
                        <z>0</z>
                        <width>527</width>
                        <height>106</height>
                        <depth>0</depth>
                        <hotspotX>0</hotspotX>
                        <hotspotY>0</hotspotY>
                        <angle>0</angle>
                        <opacity>1</opacity>
                    </world>
                </instance>
                <instance type="btnBeeBack" uid="31">
                    <properties>
                        <initial-visibility>Visible</initial-visibility>
                        <initial-animation>Default</initial-animation>
                        <initial-frame>0</initial-frame>
                        <collisions>Enabled</collisions>
                    </properties>
                    <behavior-instances>
                        <behavior-instance type="NoSave" />
                    </behavior-instances>
                    <blend-mode>0</blend-mode>
                    <effect-fallback>0</effect-fallback>
                    <world>
                        <x>1330</x>
                        <y>468</y>
                        <z>0</z>
                        <width>527</width>
                        <height>106</height>
                        <depth>0</depth>
                        <hotspotX>0</hotspotX>
                        <hotspotY>0</hotspotY>
                        <angle>0</angle>
                        <opacity>1</opacity>
                    </world>
                </instance>
                <instance type="btnBeeBack" uid="48">
                    <properties>
                        <initial-visibility>Visible</initial-visibility>
                        <initial-animation>Default</initial-animation>
                        <initial-frame>0</initial-frame>
                        <collisions>Enabled</collisions>
                    </properties>
                    <behavior-instances>
                        <behavior-instance type="NoSave" />
                    </behavior-instances>
                    <blend-mode>0</blend-mode>
                    <effect-fallback>0</effect-fallback>
                    <world>
                        <x>1330</x>
                        <y>590</y>
                        <z>0</z>
                        <width>527</width>
                        <height>106</height>
                        <depth>0</depth>
                        <hotspotX>0</hotspotX>
                        <hotspotY>0</hotspotY>
                        <angle>0</angle>
                        <opacity>1</opacity>
                    </world>
                </instance>
                <instance type="btnBeeBack" uid="49">
                    <properties>
                        <initial-visibility>Visible</initial-visibility>
                        <initial-animation>Default</initial-animation>
                        <initial-frame>0</initial-frame>
                        <collisions>Enabled</collisions>
                    </properties>
                    <behavior-instances>
                        <behavior-instance type="NoSave" />
                    </behavior-instances>
                    <blend-mode>0</blend-mode>
                    <effect-fallback>0</effect-fallback>
                    <world>
                        <x>1333</x>
                        <y>712</y>
                        <z>0</z>
                        <width>527</width>
                        <height>106</height>
                        <depth>0</depth>
                        <hotspotX>0</hotspotX>
                        <hotspotY>0</hotspotY>
                        <angle>0</angle>
                        <opacity>1</opacity>
                    </world>
                </instance>
                <instance type="arrow" uid="52">
                    <properties>
                        <initial-visibility>Visible</initial-visibility>
                        <initial-animation>Default</initial-animation>
                        <initial-frame>0</initial-frame>
                        <collisions>Enabled</collisions>
                    </properties>
                    <instance-variables>
                        <goto>4</goto>
                    </instance-variables>
                    <behavior-instances>
                        <behavior-instance type="NoSave" />
                    </behavior-instances>
                    <blend-mode>0</blend-mode>
                    <effect-fallback>0</effect-fallback>
                    <world>
                        <x>949.946289063</x>
                        <y>896.603088379</y>
                        <z>0</z>
                        <width>84</width>
                        <height>92</height>
                        <depth>0</depth>
                        <hotspotX>0.502645493</hotspotX>
                        <hotspotY>0.441176474</hotspotY>
                        <angle>-1.568058014</angle>
                        <opacity>1</opacity>
                    </world>
                </instance>
                <instance type="arrow" uid="53">
                    <properties>
                        <initial-visibility>Visible</initial-visibility>
                        <initial-animation>Default</initial-animation>
                        <initial-frame>0</initial-frame>
                        <collisions>Enabled</collisions>
                    </properties>
                    <instance-variables>
                        <goto>2</goto>
                    </instance-variables>
                    <behavior-instances>
                        <behavior-instance type="NoSave" />
                    </behavior-instances>
                    <blend-mode>0</blend-mode>
                    <effect-fallback>0</effect-fallback>
                    <world>
                        <x>962.127685547</x>
                        <y>-114.095703125</y>
                        <z>0</z>
                        <width>87</width>
                        <height>92</height>
                        <depth>0</depth>
                        <hotspotX>0.502645493</hotspotX>
                        <hotspotY>0.441176474</hotspotY>
                        <angle>1.563664317</angle>
                        <opacity>1</opacity>
                    </world>
                </instance>
            </instances>
            <effects />
        </layer>
        <layer name="texte bouton" sid="2854676617282181">
            <initially-visible>1</initially-visible>
            <background-color>255,255,255</background-color>
            <transparent>1</transparent>
            <parallax>
                <x>1</x>
                <y>1</y>
            </parallax>
            <zoom-rate>1</zoom-rate>
            <opacity>1</opacity>
            <force-own-texture>0</force-own-texture>
            <blend-mode>0</blend-mode>
            <effect-fallback>0</effect-fallback>
            <instances>
                <instance type="btnUpgrade" uid="41">
                    <properties>
                        <text>Factory storage...... aksjdhfkahsjdf kjashdf kjhasd fk</text>
                        <initial-visibility>Visible</initial-visibility>
                        <font>Arial,-32,400,0</font>
                        <color>0,0,0</color>
                        <horizontal-alignment>Left</horizontal-alignment>
                        <vertical-alignment>Top</vertical-alignment>
                        <hotspot>Top-left</hotspot>
                        <wrapping>Word</wrapping>
                        <line-height>0</line-height>
                    </properties>
                    <instance-variables>
                        <type>Factory storage</type>
                        <price>1</price>
                        <priceMutiplicator>3</priceMutiplicator>
                        <priceAdditor>1</priceAdditor>
                        <itsCabbageId>-1</itsCabbageId>
                    </instance-variables>
                    <blend-mode>0</blend-mode>
                    <effect-fallback>0</effect-fallback>
                    <world>
                        <x>710</x>
                        <y>410</y>
                        <z>0</z>
                        <width>515</width>
                        <height>83</height>
                        <depth>0</depth>
                        <hotspotX>0</hotspotX>
                        <hotspotY>0</hotspotY>
                        <angle>0</angle>
                        <opacity>1</opacity>
                    </world>
                </instance>
                <instance type="btnUpgrade" uid="43">
                    <properties>
                        <text>factory speed .......... alsdjkfl asjkdf lasjdf lkjasd</text>
                        <initial-visibility>Visible</initial-visibility>
                        <font>Arial,-32,400,0</font>
                        <color>0,0,0</color>
                        <horizontal-alignment>Left</horizontal-alignment>
                        <vertical-alignment>Top</vertical-alignment>
                        <hotspot>Top-left</hotspot>
                        <wrapping>Word</wrapping>
                        <line-height>0</line-height>
                    </properties>
                    <instance-variables>
                        <type>Factory speed</type>
                        <price>40</price>
                        <priceMutiplicator>2.5</priceMutiplicator>
                        <priceAdditor>7</priceAdditor>
                        <itsCabbageId>-1</itsCabbageId>
                    </instance-variables>
                    <blend-mode>0</blend-mode>
                    <effect-fallback>0</effect-fallback>
                    <world>
                        <x>710</x>
                        <y>654</y>
                        <z>0</z>
                        <width>515</width>
                        <height>87</height>
                        <depth>0</depth>
                        <hotspotX>0</hotspotX>
                        <hotspotY>0</hotspotY>
                        <angle>0</angle>
                        <opacity>1</opacity>
                    </world>
                </instance>
                <instance type="cabbageIcon" uid="57">
                    <properties>
                        <initial-visibility>Visible</initial-visibility>
                        <initial-animation>Default</initial-animation>
                        <initial-frame>0</initial-frame>
                        <collisions>Enabled</collisions>
                    </properties>
                    <behavior-instances>
                        <behavior-instance type="NoSave" />
                    </behavior-instances>
                    <blend-mode>0</blend-mode>
                    <effect-fallback>0</effect-fallback>
                    <world>
                        <x>747</x>
                        <y>1066</y>
                        <z>0</z>
                        <width>37.788887024</width>
                        <height>35.089679718</height>
                        <depth>0</depth>
                        <hotspotX>0.5</hotspotX>
                        <hotspotY>0.538461566</hotspotY>
                        <angle>0</angle>
                        <opacity>1</opacity>
                    </world>
                </instance>
                <instance type="btnBee" uid="59">
                    <properties>
                        <text>Bee #X speed: Current: 0.02 ... Cost:      1234</text>
                        <initial-visibility>Visible</initial-visibility>
                        <font>Arial,-32,400,0</font>
                        <color>0,0,0</color>
                        <horizontal-alignment>Left</horizontal-alignment>
                        <vertical-alignment>Top</vertical-alignment>
                        <hotspot>Top-left</hotspot>
                        <wrapping>Word</wrapping>
                        <line-height>0</line-height>
                    </properties>
                    <instance-variables>
                        <type>Bee speed</type>
                        <beeNb>1</beeNb>
                        <price>2000</price>
                        <priceMutiplicator>98</priceMutiplicator>
                        <priceAdditor>0</priceAdditor>
                        <itsCabbageId>-1</itsCabbageId>
                    </instance-variables>
                    <blend-mode>0</blend-mode>
                    <effect-fallback>0</effect-fallback>
                    <world>
                        <x>1382</x>
                        <y>357</y>
                        <z>0</z>
                        <width>515</width>
                        <height>83</height>
                        <depth>0</depth>
                        <hotspotX>0</hotspotX>
                        <hotspotY>0</hotspotY>
                        <angle>0</angle>
                        <opacity>1</opacity>
                    </world>
                </instance>
                <instance type="btnBee" uid="60">
                    <properties>
                        <text>Buy Bee #X ................................... Cost: 1234</text>
                        <initial-visibility>Visible</initial-visibility>
                        <font>Arial,-32,400,0</font>
                        <color>0,0,0</color>
                        <horizontal-alignment>Left</horizontal-alignment>
                        <vertical-alignment>Top</vertical-alignment>
                        <hotspot>Top-left</hotspot>
                        <wrapping>Word</wrapping>
                        <line-height>0</line-height>
                    </properties>
                    <instance-variables>
                        <type>Buy bee</type>
                        <beeNb>2</beeNb>
                        <price>100</price>
                        <priceMutiplicator>98</priceMutiplicator>
                        <priceAdditor>0</priceAdditor>
                        <itsCabbageId>-1</itsCabbageId>
                    </instance-variables>
                    <blend-mode>0</blend-mode>
                    <effect-fallback>0</effect-fallback>
                    <world>
                        <x>1382</x>
                        <y>478</y>
                        <z>0</z>
                        <width>515</width>
                        <height>83</height>
                        <depth>0</depth>
                        <hotspotX>0</hotspotX>
                        <hotspotY>0</hotspotY>
                        <angle>0</angle>
                        <opacity>1</opacity>
                    </world>
                </instance>
                <instance type="btnBee" uid="61">
                    <properties>
                        <text>Buy Bee #X ................................... Cost: 1234</text>
                        <initial-visibility>Visible</initial-visibility>
                        <font>Arial,-32,400,0</font>
                        <color>0,0,0</color>
                        <horizontal-alignment>Left</horizontal-alignment>
                        <vertical-alignment>Top</vertical-alignment>
                        <hotspot>Top-left</hotspot>
                        <wrapping>Word</wrapping>
                        <line-height>0</line-height>
                    </properties>
                    <instance-variables>
                        <type>Buy bee</type>
                        <beeNb>3</beeNb>
                        <price>500</price>
                        <priceMutiplicator>98</priceMutiplicator>
                        <priceAdditor>0</priceAdditor>
                        <itsCabbageId>-1</itsCabbageId>
                    </instance-variables>
                    <blend-mode>0</blend-mode>
                    <effect-fallback>0</effect-fallback>
                    <world>
                        <x>1382</x>
                        <y>598</y>
                        <z>0</z>
                        <width>515</width>
                        <height>83</height>
                        <depth>0</depth>
                        <hotspotX>0</hotspotX>
                        <hotspotY>0</hotspotY>
                        <angle>0</angle>
                        <opacity>1</opacity>
                    </world>
                </instance>
                <instance type="btnBee" uid="62">
                    <properties>
                        <text>Buy Bee #X ................................... Cost: 1234</text>
                        <initial-visibility>Visible</initial-visibility>
                        <font>Arial,-32,400,0</font>
                        <color>0,0,0</color>
                        <horizontal-alignment>Left</horizontal-alignment>
                        <vertical-alignment>Top</vertical-alignment>
                        <hotspot>Top-left</hotspot>
                        <wrapping>Word</wrapping>
                        <line-height>0</line-height>
                    </properties>
                    <instance-variables>
                        <type>Buy bee</type>
                        <beeNb>4</beeNb>
                        <price>1200</price>
                        <priceMutiplicator>98</priceMutiplicator>
                        <priceAdditor>0</priceAdditor>
                        <itsCabbageId>-1</itsCabbageId>
                    </instance-variables>
                    <blend-mode>0</blend-mode>
                    <effect-fallback>0</effect-fallback>
                    <world>
                        <x>1382</x>
                        <y>719</y>
                        <z>0</z>
                        <width>515</width>
                        <height>83</height>
                        <depth>0</depth>
                        <hotspotX>0</hotspotX>
                        <hotspotY>0</hotspotY>
                        <angle>0</angle>
                        <opacity>1</opacity>
                    </world>
                </instance>
                <instance type="btnUpgrade" uid="42">
                    <properties>
                        <text>factory productivity.......... alsdjkfl asjkdf lasjdf lkjasd</text>
                        <initial-visibility>Visible</initial-visibility>
                        <font>Arial,-32,400,0</font>
                        <color>0,0,0</color>
                        <horizontal-alignment>Left</horizontal-alignment>
                        <vertical-alignment>Top</vertical-alignment>
                        <hotspot>Top-left</hotspot>
                        <wrapping>Word</wrapping>
                        <line-height>0</line-height>
                    </properties>
                    <instance-variables>
                        <type>Factory productivity</type>
                        <price>1</price>
                        <priceMutiplicator>2</priceMutiplicator>
                        <priceAdditor>5</priceAdditor>
                        <itsCabbageId>-1</itsCabbageId>
                    </instance-variables>
                    <blend-mode>0</blend-mode>
                    <effect-fallback>0</effect-fallback>
                    <world>
                        <x>710</x>
                        <y>532</y>
                        <z>0</z>
                        <width>515</width>
                        <height>87</height>
                        <depth>0</depth>
                        <hotspotX>0</hotspotX>
                        <hotspotY>0</hotspotY>
                        <angle>0</angle>
                        <opacity>1</opacity>
                    </world>
                </instance>
            </instances>
            <effects />
        </layer>
        <layer name="game" sid="5945919947284653">
            <initially-visible>1</initially-visible>
            <background-color>255,255,255</background-color>
            <transparent>1</transparent>
            <parallax>
                <x>1</x>
                <y>1</y>
            </parallax>
            <zoom-rate>1</zoom-rate>
            <opacity>1</opacity>
            <force-own-texture>0</force-own-texture>
            <blend-mode>0</blend-mode>
            <effect-fallback>0</effect-fallback>
            <instances>
                <instance type="beeCollectZone" uid="7">
                    <properties>
                        <initial-visibility>Invisible</initial-visibility>
                        <initial-animation>Default</initial-animation>
                        <initial-frame>0</initial-frame>
                        <collisions>Enabled</collisions>
                    </properties>
                    <blend-mode>0</blend-mode>
                    <effect-fallback>0</effect-fallback>
                    <world>
                        <x>302</x>
                        <y>330</y>
                        <z>0</z>
                        <width>75</width>
                        <height>48</height>
                        <depth>0</depth>
                        <hotspotX>0.5</hotspotX>
                        <hotspotY>0.5</hotspotY>
                        <angle>0</angle>
                        <opacity>0.400000006</opacity>
                    </world>
                </instance>
                <instance type="beeDropZone" uid="17">
                    <properties>
                        <initial-visibility>Invisible</initial-visibility>
                        <initial-animation>Default</initial-animation>
                        <initial-frame>0</initial-frame>
                        <collisions>Enabled</collisions>
                    </properties>
                    <behavior-instances>
                        <behavior-instance type="NoSave" />
                    </behavior-instances>
                    <blend-mode>0</blend-mode>
                    <effect-fallback>0</effect-fallback>
                    <world>
                        <x>62</x>
                        <y>736</y>
                        <z>0</z>
                        <width>86</width>
                        <height>38</height>
                        <depth>0</depth>
                        <hotspotX>0</hotspotX>
                        <hotspotY>1</hotspotY>
                        <angle>0</angle>
                        <opacity>0.400000006</opacity>
                    </world>
                </instance>
                <instance type="water" uid="15">
                    <properties>
                        <initial-visibility>Visible</initial-visibility>
                        <initial-animation>Default</initial-animation>
                        <initial-frame>0</initial-frame>
                        <collisions>Enabled</collisions>
                    </properties>
                    <behavior-instances>
                        <behavior-instance type="NoSave" />
                    </behavior-instances>
                    <blend-mode>0</blend-mode>
                    <effect-fallback>0</effect-fallback>
                    <world>
                        <x>320</x>
                        <y>577</y>
                        <z>0</z>
                        <width>640</width>
                        <height>57</height>
                        <depth>0</depth>
                        <hotspotX>0.5</hotspotX>
                        <hotspotY>0.5</hotspotY>
                        <angle>0</angle>
                        <opacity>1</opacity>
                    </world>
                </instance>
                <instance type="cabbage" uid="16">
                    <properties>
                        <initial-visibility>Visible</initial-visibility>
                        <initial-animation>Default</initial-animation>
                        <initial-frame>0</initial-frame>
                        <collisions>Enabled</collisions>
                    </properties>
                    <instance-variables>
                        <beeTargeted>false</beeTargeted>
                    </instance-variables>
                    <behavior-instances>
                        <behavior-instance type="Physics">
                            <properties>
                                <immovable>No</immovable>
                                <collision-mask>Circle</collision-mask>
                                <prevent-rotation>No</prevent-rotation>
                                <density>10</density>
                                <friction>0.1</friction>
                                <elasticity>0.3</elasticity>
                                <linear-damping>0</linear-damping>
                                <angular-damping>0.01</angular-damping>
                                <bullet>No</bullet>
                                <initial-state>Enabled</initial-state>
                            </properties>
                        </behavior-instance>
                        <behavior-instance type="NoSave" />
                    </behavior-instances>
                    <blend-mode>0</blend-mode>
                    <effect-fallback>0</effect-fallback>
                    <world>
                        <x>-177</x>
                        <y>862</y>
                        <z>0</z>
                        <width>14</width>
                        <height>13</height>
                        <depth>0</depth>
                        <hotspotX>0.5</hotspotX>
                        <hotspotY>0.538461566</hotspotY>
                        <angle>0</angle>
                        <opacity>1</opacity>
                    </world>
                </instance>
                <instance type="factory" uid="14">
                    <properties>
                        <initial-visibility>Visible</initial-visibility>
                        <initial-animation>Default</initial-animation>
                        <initial-frame>0</initial-frame>
                        <collisions>Enabled</collisions>
                    </properties>
                    <instance-variables>
                        <cabbages>0</cabbages>
                        <maxStorage>5</maxStorage>
                        <productivity>1</productivity>
                        <timer>0</timer>
                        <price>1</price>
                        <speed>1</speed>
                        <timerLength>10</timerLength>
                        <convertedInLastMinute>0</convertedInLastMinute>
                        <currentProductionPerMinute>0</currentProductionPerMinute>
                    </instance-variables>
                    <blend-mode>0</blend-mode>
                    <effect-fallback>0</effect-fallback>
                    <world>
                        <x>342</x>
                        <y>786</y>
                        <z>0</z>
                        <width>184.526580811</width>
                        <height>171.063278198</height>
                        <depth>0</depth>
                        <hotspotX>0.506437778</hotspotX>
                        <hotspotY>0.513888896</hotspotY>
                        <angle>0</angle>
                        <opacity>1</opacity>
                    </world>
                </instance>
                <instance type="plus1" uid="6">
                    <properties>
                        <text>+1</text>
                        <initial-visibility>Visible</initial-visibility>
                        <font>Arial,-27,400,0</font>
                        <color>0,204,51</color>
                        <horizontal-alignment>Left</horizontal-alignment>
                        <vertical-alignment>Top</vertical-alignment>
                        <hotspot>Center</hotspot>
                        <wrapping>Word</wrapping>
                        <line-height>0</line-height>
                    </properties>
                    <behavior-instances>
                        <behavior-instance type="Bullet">
                            <properties>
                                <speed>40</speed>
                                <acceleration>0</acceleration>
                                <gravity>0</gravity>
                                <bounce-off-solids>No</bounce-off-solids>
                                <set-angle>No</set-angle>
                                <initial-state>Enabled</initial-state>
                            </properties>
                        </behavior-instance>
                        <behavior-instance type="Fade">
                            <properties>
                                <active-at-start>Yes</active-at-start>
                                <fade-in-time>0</fade-in-time>
                                <wait-time>0</wait-time>
                                <fade-out-time>1</fade-out-time>
                                <destroy>After fade out</destroy>
                            </properties>
                        </behavior-instance>
                        <behavior-instance type="NoSave" />
                    </behavior-instances>
                    <blend-mode>0</blend-mode>
                    <effect-fallback>0</effect-fallback>
                    <world>
                        <x>-241</x>
                        <y>703</y>
                        <z>0</z>
                        <width>253</width>
                        <height>62</height>
                        <depth>0</depth>
                        <hotspotX>0.5</hotspotX>
                        <hotspotY>0.5</hotspotY>
                        <angle>0</angle>
                        <opacity>1</opacity>
                    </world>
                </instance>
                <instance type="waterParticles" uid="27">
                    <properties>
                        <rate>15</rate>
                        <spray-cone>90</spray-cone>
                        <type>One-shot</type>
                        <initial-particle-properties></initial-particle-properties>
                        <speed>100</speed>
                        <size>16</size>
                        <opacity>100</opacity>
                        <grow-rate>5</grow-rate>
                        <x-randomiser>0</x-randomiser>
                        <y-randomiser>0</y-randomiser>
                        <speed-randomiser->150</speed-randomiser->
                        <size-randomiser>0</size-randomiser>
                        <grow-rate-randomiser>0</grow-rate-randomiser>
                        <particle-lifetime-properties></particle-lifetime-properties>
                        <acceleration>0</acceleration>
                        <gravity>300</gravity>
                        <angle-randomiser>0</angle-randomiser>
                        <speed-randomiser>0</speed-randomiser>
                        <opacity-randomiser>0</opacity-randomiser>
                        <destroy-mode>Fade to invisible</destroy-mode>
                        <timeout>1</timeout>
                    </properties>
                    <behavior-instances>
                        <behavior-instance type="NoSave" />
                    </behavior-instances>
                    <blend-mode>0</blend-mode>
                    <effect-fallback>0</effect-fallback>
                    <world>
                        <x>-200</x>
                        <y>740</y>
                        <z>0</z>
                        <width>128</width>
                        <height>128</height>
                        <depth>0</depth>
                        <hotspotX>0</hotspotX>
                        <hotspotY>0.5</hotspotY>
                        <angle>-1.570796371</angle>
                        <opacity>1</opacity>
                    </world>
                </instance>
                <instance type="menhir" uid="3">
                    <properties>
                        <initial-visibility>Visible</initial-visibility>
                        <initial-animation>Default</initial-animation>
                        <initial-frame>0</initial-frame>
                        <collisions>Enabled</collisions>
                    </properties>
                    <instance-variables>
                        <tooltipText>Enlarge your menhir! Cost only %p salads. Click to buy. (100% natural product)</tooltipText>
                        <price>1</price>
                        <upgrades>0</upgrades>
                    </instance-variables>
                    <behavior-instances>
                        <behavior-instance type="Physics">
                            <properties>
                                <immovable>Yes</immovable>
                                <collision-mask>Use collision polygon</collision-mask>
                                <prevent-rotation>Yes</prevent-rotation>
                                <density>1</density>
                                <friction>0.5</friction>
                                <elasticity>0.2</elasticity>
                                <linear-damping>0</linear-damping>
                                <angular-damping>0.01</angular-damping>
                                <bullet>No</bullet>
                                <initial-state>Enabled</initial-state>
                            </properties>
                        </behavior-instance>
                    </behavior-instances>
                    <blend-mode>0</blend-mode>
                    <effect-fallback>0</effect-fallback>
                    <world>
                        <x>301</x>
                        <y>470</y>
                        <z>0</z>
                        <width>77</width>
                        <height>283.200012207</height>
                        <depth>0</depth>
                        <hotspotX>0.5</hotspotX>
                        <hotspotY>0.416666657</hotspotY>
                        <angle>0</angle>
                        <opacity>1</opacity>
                    </world>
                </instance>
                <instance type="cabbage" uid="37">
                    <properties>
                        <initial-visibility>Visible</initial-visibility>
                        <initial-animation>Default</initial-animation>
                        <initial-frame>0</initial-frame>
                        <collisions>Enabled</collisions>
                    </properties>
                    <instance-variables>
                        <beeTargeted>false</beeTargeted>
                    </instance-variables>
                    <behavior-instances>
                        <behavior-instance type="Physics">
                            <properties>
                                <immovable>No</immovable>
                                <collision-mask>Circle</collision-mask>
                                <prevent-rotation>No</prevent-rotation>
                                <density>10</density>
                                <friction>0.1</friction>
                                <elasticity>0.3</elasticity>
                                <linear-damping>0</linear-damping>
                                <angular-damping>0.01</angular-damping>
                                <bullet>No</bullet>
                                <initial-state>Enabled</initial-state>
                            </properties>
                        </behavior-instance>
                        <behavior-instance type="NoSave" />
                    </behavior-instances>
                    <blend-mode>0</blend-mode>
                    <effect-fallback>0</effect-fallback>
                    <world>
                        <x>293</x>
                        <y>-146</y>
                        <z>0</z>
                        <width>14</width>
                        <height>13</height>
                        <depth>0</depth>
                        <hotspotX>0.5</hotspotX>
                        <hotspotY>0.538461566</hotspotY>
                        <angle>0</angle>
                        <opacity>1</opacity>
                    </world>
                </instance>
                <instance type="bee" uid="39">
                    <properties>
                        <initial-visibility>Visible</initial-visibility>
                        <initial-animation>Default</initial-animation>
                        <initial-frame>0</initial-frame>
                        <collisions>Enabled</collisions>
                    </properties>
                    <instance-variables>
                        <numéro>1</numéro>
                        <speed>0.02</speed>
                        <status>collect</status>
                        <cabbageID>-1</cabbageID>
                        <targetX>0</targetX>
                        <targetY>0</targetY>
                    </instance-variables>
                    <blend-mode>0</blend-mode>
                    <effect-fallback>0</effect-fallback>
                    <world>
                        <x>160</x>
                        <y>461</y>
                        <z>0</z>
                        <width>37</width>
                        <height>30</height>
                        <depth>0</depth>
                        <hotspotX>0.740259767</hotspotX>
                        <hotspotY>0.828125</hotspotY>
                        <angle>0</angle>
                        <opacity>1</opacity>
                    </world>
                </instance>
                <instance type="solidBloc" uid="2">
                    <properties>
                        <initial-visibility>Visible</initial-visibility>
                        <initial-animation>Default</initial-animation>
                        <initial-frame>0</initial-frame>
                        <collisions>Enabled</collisions>
                    </properties>
                    <behavior-instances>
                        <behavior-instance type="Physics">
                            <properties>
                                <immovable>Yes</immovable>
                                <collision-mask>Bounding box</collision-mask>
                                <prevent-rotation>Yes</prevent-rotation>
                                <density>1</density>
                                <friction>0.5</friction>
                                <elasticity>0.2</elasticity>
                                <linear-damping>0</linear-damping>
                                <angular-damping>0.01</angular-damping>
                                <bullet>No</bullet>
                                <initial-state>Enabled</initial-state>
                            </properties>
                        </behavior-instance>
                        <behavior-instance type="NoSave" />
                    </behavior-instances>
                    <blend-mode>0</blend-mode>
                    <effect-fallback>0</effect-fallback>
                    <world>
                        <x>145</x>
                        <y>818</y>
                        <z>0</z>
                        <width>7</width>
                        <height>239</height>
                        <depth>0</depth>
                        <hotspotX>0.5</hotspotX>
                        <hotspotY>0.5</hotspotY>
                        <angle>-1.124453664</angle>
                        <opacity>1</opacity>
                    </world>
                </instance>
                <instance type="tamagotchi" uid="54">
                    <properties>
                        <initial-visibility>Visible</initial-visibility>
                        <initial-animation>Default</initial-animation>
                        <initial-frame>0</initial-frame>
                        <collisions>Enabled</collisions>
                    </properties>
                    <instance-variables>
                        <name>Vérachou</name>
                        <age>0</age>
                        <animation>normal</animation>
                        <hungry>4</hungry>
                        <hungryMax>6</hungryMax>
                        <hungryCounter>1000</hungryCounter>
                        <hungryCounterMax>7200</hungryCounterMax>
                        <energy>5</energy>
                        <energyMax>5</energyMax>
                        <energyCounter>0</energyCounter>
                        <energyCounterMax>3600</energyCounterMax>
                        <IQ>0</IQ>
                    </instance-variables>
                    <blend-mode>0</blend-mode>
                    <effect-fallback>0</effect-fallback>
                    <world>
                        <x>966</x>
                        <y>-475</y>
                        <z>0</z>
                        <width>78</width>
                        <height>79</height>
                        <depth>0</depth>
                        <hotspotX>0.461538464</hotspotX>
                        <hotspotY>0.962025344</hotspotY>
                        <angle>0</angle>
                        <opacity>1</opacity>
                    </world>
                </instance>
                <instance type="tamagoStats" uid="55">
                    <properties>
                        <text>Tamagotchi stats</text>
                        <initial-visibility>Visible</initial-visibility>
                        <font>Arial,-27,400,0</font>
                        <color>255,255,255</color>
                        <horizontal-alignment>Center</horizontal-alignment>
                        <vertical-alignment>Top</vertical-alignment>
                        <hotspot>Top-left</hotspot>
                        <wrapping>Word</wrapping>
                        <line-height>0</line-height>
                    </properties>
                    <behavior-instances>
                        <behavior-instance type="NoSave" />
                    </behavior-instances>
                    <blend-mode>0</blend-mode>
                    <effect-fallback>0</effect-fallback>
                    <world>
                        <x>751</x>
                        <y>-433</y>
                        <z>0</z>
                        <width>433</width>
                        <height>223</height>
                        <depth>0</depth>
                        <hotspotX>0</hotspotX>
                        <hotspotY>0</hotspotY>
                        <angle>0</angle>
                        <opacity>1</opacity>
                    </world>
                </instance>
                <instance type="tamagoFeedBtn" uid="63">
                    <properties>
                        <initial-visibility>Visible</initial-visibility>
                        <initial-animation>Default</initial-animation>
                        <initial-frame>0</initial-frame>
                        <collisions>Enabled</collisions>
                    </properties>
                    <instance-variables>
                        <energyCost>1</energyCost>
                    </instance-variables>
                    <blend-mode>0</blend-mode>
                    <effect-fallback>0</effect-fallback>
                    <world>
                        <x>735</x>
                        <y>-568</y>
                        <z>0</z>
                        <width>68.978256226</width>
                        <height>68.978256226</height>
                        <depth>0</depth>
                        <hotspotX>0.5</hotspotX>
                        <hotspotY>0.5</hotspotY>
                        <angle>0</angle>
                        <opacity>1</opacity>
                    </world>
                </instance>
            </instances>
            <effects />
        </layer>
        <layer name="UI" sid="6062488894345962">
            <initially-visible>1</initially-visible>
            <background-color>255,255,255</background-color>
            <transparent>1</transparent>
            <parallax>
                <x>1</x>
                <y>1</y>
            </parallax>
            <zoom-rate>1</zoom-rate>
            <opacity>1</opacity>
            <force-own-texture>0</force-own-texture>
            <blend-mode>0</blend-mode>
            <effect-fallback>0</effect-fallback>
            <instances>
                <instance type="camera" uid="9">
                    <properties>
                        <initial-visibility>Invisible</initial-visibility>
                        <initial-animation>Default</initial-animation>
                        <initial-frame>0</initial-frame>
                        <collisions>Enabled</collisions>
                    </properties>
                    <instance-variables>
                        <screen>1</screen>
                    </instance-variables>
                    <behavior-instances>
                        <behavior-instance type="ScrollTo">
                            <properties>
                                <initial-state>Enabled</initial-state>
                            </properties>
                        </behavior-instance>
                        <behavior-instance type="NoSave" />
                    </behavior-instances>
                    <blend-mode>0</blend-mode>
                    <effect-fallback>0</effect-fallback>
                    <world>
                        <x>320.296020508</x>
                        <y>480.269989014</y>
                        <z>0</z>
                        <width>129.647994995</width>
                        <height>118.260002136</height>
                        <depth>0</depth>
                        <hotspotX>0.502283096</hotspotX>
                        <hotspotY>0.502283096</hotspotY>
                        <angle>0</angle>
                        <opacity>1</opacity>
                    </world>
                </instance>
                <instance type="txtFactory" uid="21">
                    <properties>
                        <text>salad factory 88/20</text>
                        <initial-visibility>Visible</initial-visibility>
                        <font>Arial,-27,400,0</font>
                        <color>255,255,255</color>
                        <horizontal-alignment>Left</horizontal-alignment>
                        <vertical-alignment>Top</vertical-alignment>
                        <hotspot>Top-left</hotspot>
                        <wrapping>Word</wrapping>
                        <line-height>0</line-height>
                    </properties>
                    <behavior-instances>
                        <behavior-instance type="NoSave" />
                    </behavior-instances>
                    <blend-mode>0</blend-mode>
                    <effect-fallback>0</effect-fallback>
                    <world>
                        <x>252</x>
                        <y>791</y>
                        <z>0</z>
                        <width>207</width>
                        <height>97</height>
                        <depth>0</depth>
                        <hotspotX>0</hotspotX>
                        <hotspotY>0</hotspotY>
                        <angle>0</angle>
                        <opacity>1</opacity>
                    </world>
                </instance>
                <instance type="UIShit" uid="28">
                    <properties>
                        <text>Lorem Ipsum fucking big text</text>
                        <initial-visibility>Visible</initial-visibility>
                        <font>Arial,-27,400,0</font>
                        <color>255,255,255</color>
                        <horizontal-alignment>Left</horizontal-alignment>
                        <vertical-alignment>Top</vertical-alignment>
                        <hotspot>Top-left</hotspot>
                        <wrapping>Word</wrapping>
                        <line-height>0</line-height>
                    </properties>
                    <behavior-instances>
                        <behavior-instance type="NoSave" />
                    </behavior-instances>
                    <blend-mode>0</blend-mode>
                    <effect-fallback>0</effect-fallback>
                    <world>
                        <x>23</x>
                        <y>99</y>
                        <z>0</z>
                        <width>433</width>
                        <height>292</height>
                        <depth>0</depth>
                        <hotspotX>0</hotspotX>
                        <hotspotY>0</hotspotY>
                        <angle>0</angle>
                        <opacity>1</opacity>
                    </world>
                </instance>
                <instance type="UIShit" uid="26">
                    <properties>
                        <text>Lorem Ipsum fucking big text</text>
                        <initial-visibility>Visible</initial-visibility>
                        <font>Arial,-27,400,0</font>
                        <color>255,255,255</color>
                        <horizontal-alignment>Left</horizontal-alignment>
                        <vertical-alignment>Top</vertical-alignment>
                        <hotspot>Top-left</hotspot>
                        <wrapping>Word</wrapping>
                        <line-height>0</line-height>
                    </properties>
                    <behavior-instances>
                        <behavior-instance type="NoSave" />
                    </behavior-instances>
                    <blend-mode>0</blend-mode>
                    <effect-fallback>0</effect-fallback>
                    <world>
                        <x>707</x>
                        <y>99</y>
                        <z>0</z>
                        <width>433</width>
                        <height>281</height>
                        <depth>0</depth>
                        <hotspotX>0</hotspotX>
                        <hotspotY>0</hotspotY>
                        <angle>0</angle>
                        <opacity>1</opacity>
                    </world>
                </instance>
                <instance type="factoryProgressBar" uid="25">
                    <properties>
                        <initial-visibility>Visible</initial-visibility>
                        <initial-animation>Default</initial-animation>
                        <initial-frame>0</initial-frame>
                        <collisions>Enabled</collisions>
                    </properties>
                    <behavior-instances>
                        <behavior-instance type="NoSave" />
                    </behavior-instances>
                    <blend-mode>0</blend-mode>
                    <effect-fallback>0</effect-fallback>
                    <world>
                        <x>252</x>
                        <y>861</y>
                        <z>0</z>
                        <width>177</width>
                        <height>9</height>
                        <depth>0</depth>
                        <hotspotX>0</hotspotX>
                        <hotspotY>0.555555582</hotspotY>
                        <angle>0</angle>
                        <opacity>1</opacity>
                    </world>
                </instance>
                <instance type="tooltips" uid="29">
                    <properties>
                        <text>tooltip txtbox</text>
                        <initial-visibility>Visible</initial-visibility>
                        <font>Arial,-27,400,0</font>
                        <color>255,255,255</color>
                        <horizontal-alignment>Left</horizontal-alignment>
                        <vertical-alignment>Top</vertical-alignment>
                        <hotspot>Center</hotspot>
                        <wrapping>Word</wrapping>
                        <line-height>0</line-height>
                    </properties>
                    <behavior-instances>
                        <behavior-instance type="NoSave" />
                    </behavior-instances>
                    <blend-mode>0</blend-mode>
                    <effect-fallback>0</effect-fallback>
                    <world>
                        <x>223</x>
                        <y>1001</y>
                        <z>0</z>
                        <width>438</width>
                        <height>126</height>
                        <depth>0</depth>
                        <hotspotX>0.5</hotspotX>
                        <hotspotY>0.5</hotspotY>
                        <angle>0</angle>
                        <opacity>1</opacity>
                    </world>
                </instance>
                <instance type="UIShit" uid="19">
                    <properties>
                        <text>Lorem Ipsum fucking big text</text>
                        <initial-visibility>Visible</initial-visibility>
                        <font>Arial,-27,400,0</font>
                        <color>255,255,255</color>
                        <horizontal-alignment>Left</horizontal-alignment>
                        <vertical-alignment>Top</vertical-alignment>
                        <hotspot>Top-left</hotspot>
                        <wrapping>Word</wrapping>
                        <line-height>0</line-height>
                    </properties>
                    <behavior-instances>
                        <behavior-instance type="NoSave" />
                    </behavior-instances>
                    <blend-mode>0</blend-mode>
                    <effect-fallback>0</effect-fallback>
                    <world>
                        <x>1369</x>
                        <y>102</y>
                        <z>0</z>
                        <width>433</width>
                        <height>292</height>
                        <depth>0</depth>
                        <hotspotX>0</hotspotX>
                        <hotspotY>0</hotspotY>
                        <angle>0</angle>
                        <opacity>1</opacity>
                    </world>
                </instance>
                <instance type="UIShit" uid="56">
                    <properties>
                        <text>Lorem Ipsum fucking big text</text>
                        <initial-visibility>Visible</initial-visibility>
                        <font>Arial,-27,400,0</font>
                        <color>255,255,255</color>
                        <horizontal-alignment>Left</horizontal-alignment>
                        <vertical-alignment>Top</vertical-alignment>
                        <hotspot>Top-left</hotspot>
                        <wrapping>Word</wrapping>
                        <line-height>0</line-height>
                    </properties>
                    <behavior-instances>
                        <behavior-instance type="NoSave" />
                    </behavior-instances>
                    <blend-mode>0</blend-mode>
                    <effect-fallback>0</effect-fallback>
                    <world>
                        <x>670</x>
                        <y>-918</y>
                        <z>0</z>
                        <width>433</width>
                        <height>214</height>
                        <depth>0</depth>
                        <hotspotX>0</hotspotX>
                        <hotspotY>0</hotspotY>
                        <angle>0</angle>
                        <opacity>1</opacity>
                    </world>
                </instance>
            </instances>
            <effects />
        </layer>
        <layer name="notifications" sid="2341121289213795">
            <initially-visible>1</initially-visible>
            <background-color>255,255,255</background-color>
            <transparent>1</transparent>
            <parallax>
                <x>0</x>
                <y>0</y>
            </parallax>
            <zoom-rate>1</zoom-rate>
            <opacity>1</opacity>
            <force-own-texture>0</force-own-texture>
            <blend-mode>0</blend-mode>
            <effect-fallback>0</effect-fallback>
            <instances>
                <instance type="notificationBox" uid="34">
                    <properties>
                        <initial-visibility>Visible</initial-visibility>
                        <initial-animation>Default</initial-animation>
                        <initial-frame>0</initial-frame>
                        <collisions>Enabled</collisions>
                    </properties>
                    <instance-variables>
                        <ouverte>false</ouverte>
                    </instance-variables>
                    <behavior-instances>
                        <behavior-instance type="NoSave" />
                    </behavior-instances>
                    <blend-mode>0</blend-mode>
                    <effect-fallback>0</effect-fallback>
                    <world>
                        <x>0</x>
                        <y>0</y>
                        <z>0</z>
                        <width>640</width>
                        <height>73</height>
                        <depth>0</depth>
                        <hotspotX>0</hotspotX>
                        <hotspotY>0</hotspotY>
                        <angle>0</angle>
                        <opacity>0.899999976</opacity>
                    </world>
                </instance>
                <instance type="txtNotifications" uid="36">
                    <properties>
                        <text>Notification log............................ No notifications received yet</text>
                        <initial-visibility>Visible</initial-visibility>
                        <font>Arial,-24,400,0</font>
                        <color>255,255,255</color>
                        <horizontal-alignment>Center</horizontal-alignment>
                        <vertical-alignment>Top</vertical-alignment>
                        <hotspot>Top-left</hotspot>
                        <wrapping>Word</wrapping>
                        <line-height>0</line-height>
                    </properties>
                    <instance-variables>
                        <grand>false</grand>
                    </instance-variables>
                    <behavior-instances>
                        <behavior-instance type="NoSave" />
                    </behavior-instances>
                    <blend-mode>0</blend-mode>
                    <effect-fallback>0</effect-fallback>
                    <world>
                        <x>8</x>
                        <y>5</y>
                        <z>0</z>
                        <width>609</width>
                        <height>66</height>
                        <depth>0</depth>
                        <hotspotX>0</hotspotX>
                        <hotspotY>0</hotspotY>
                        <angle>0</angle>
                        <opacity>1</opacity>
                    </world>
                </instance>
                <instance type="txtNotifications" uid="35">
                    <properties>
                        <text>Notification log............................ No notifications received yet</text>
                        <initial-visibility>Invisible</initial-visibility>
                        <font>Arial,-29,400,0</font>
                        <color>255,255,255</color>
                        <horizontal-alignment>Left</horizontal-alignment>
                        <vertical-alignment>Top</vertical-alignment>
                        <hotspot>Top-left</hotspot>
                        <wrapping>Word</wrapping>
                        <line-height>6</line-height>
                    </properties>
                    <instance-variables>
                        <grand>true</grand>
                    </instance-variables>
                    <behavior-instances>
                        <behavior-instance type="NoSave" />
                    </behavior-instances>
                    <blend-mode>0</blend-mode>
                    <effect-fallback>0</effect-fallback>
                    <world>
                        <x>21</x>
                        <y>6</y>
                        <z>0</z>
                        <width>595</width>
                        <height>208</height>
                        <depth>0</depth>
                        <hotspotX>0</hotspotX>
                        <hotspotY>0</hotspotY>
                        <angle>0</angle>
                        <opacity>1</opacity>
                    </world>
                </instance>
            </instances>
            <effects />
        </layer>
    </layers>
    <nonworld-instances>
        <instance type="Date" uid="0" />
        <instance type="notifications" uid="33">
            <properties>
                <width>0</width>
                <height>1</height>
                <depth>1</depth>
            </properties>
        </instance>
        <instance type="sillyMessages" uid="50">
            <properties>
                <width>10</width>
                <height>1</height>
                <depth>1</depth>
            </properties>
        </instance>
    </nonworld-instances>
    <effects />
</c2layout>
